<xml xmlns="http://www.w3.org/1999/xhtml">
  <block type="movement_forward" id="11" x="35" y="39">
    <next>
      <block type="robot_delay" id="72" inline="true">
        <value name="DELAY">
          <block type="math_number" id="79">
            <field name="NUM">4000</field>
          </block>
        </value>
        <next>
          <block type="movement_forward" id="21">
            <next>
              <block type="movement_forward" id="31">
                <next>
                  <block type="movement_reverse" id="41">
                    <next>
                      <block type="movement_forward" id="51">
                        <next>
                          <block type="movement_left" id="61"></block>
                        </next>
                      </block>
                    </next>
                  </block>
                </next>
              </block>
            </next>
          </block>
        </next>
      </block>
    </next>
  </block>
</xml>